{
  "institutionId": "guilford-county",
  "schoolYear": "2027-2028",
  "firstDay": "2027-08-23",
  "lastDay": "2028-06-08",
  "totalSchoolDays": 185,
  "teacherWorkDays": 200,
  "semesters": 2,
  "sourceUrl": "https://www.gcsnc.com/calendar",
  "sourcePdfUrl": "",
  "lastVerifiedAt": "2026-07-05",
  "events": [
    {
      "date": "2027-08-23",
      "name": "First Day of School",
      "type": "school_start"
    },
    {
      "date": "2027-09-06",
      "name": "Labor Day",
      "type": "holiday"
    },
    {
      "date": "2027-11-11",
      "name": "Veterans Day",
      "type": "holiday"
    },
    {
      "date": "2027-11-24",
      "name": "Thanksgiving Break",
      "type": "break_start"
    },
    {
      "date": "2027-11-27",
      "name": "Thanksgiving Break End",
      "type": "break_end"
    },
    {
      "date": "2027-12-20",
      "name": "Winter Break",
      "type": "break_start"
    },
    {
      "date": "2027-12-31",
      "name": "Winter Break End",
      "type": "break_end"
    },
    {
      "date": "2028-01-17",
      "name": "Martin Luther King Jr. Day",
      "type": "holiday"
    },
    {
      "date": "2028-04-10",
      "name": "Spring Break",
      "type": "break_start"
    },
    {
      "date": "2028-04-14",
      "name": "Spring Break End",
      "type": "break_end"
    },
    {
      "date": "2028-05-29",
      "name": "Memorial Day",
      "type": "holiday"
    },
    {
      "date": "2028-06-08",
      "name": "Last Day of School",
      "type": "school_end"
    }
  ],
  "calendarNotes": "Guilford County Schools begins the 2027–2028 school year on August 23, 2027. Spring Break runs April 10–14, 2028 — the same week as Charlotte-Mecklenburg Schools, a rare shared window between the two districts. The school year ends June 8, 2028."
}
